smspdudecoder/__init__.py
smspdudecoder/codecs.py
smspdudecoder/easy.py
smspdudecoder/elements.py
smspdudecoder/fields.py
smspdudecoder-2.2.0.dist-info/LICENSE
smspdudecoder-2.2.0.dist-info/METADATA
smspdudecoder-2.2.0.dist-info/WHEEL
smspdudecoder-2.2.0.dist-info/top_level.txt
smspdudecoder-2.2.0.dist-info/RECORD
