Metadata-Version: 2.1
Name: smspdudecoder
Version: 2.2.0
Summary: Python SMS PDU Decoder
Home-page: https://github.com/qotto/smspdudecoder
Author: Alexandre Syenchuk
Author-email: sacha@qotto.net
License: MIT
Classifier: Development Status :: 5 - Production/Stable
Classifier: Intended Audience :: Developers
Classifier: Intended Audience :: Telecommunications Industry
Classifier: License :: OSI Approved :: MIT License
Classifier: Topic :: Communications :: Telephony
Classifier: Programming Language :: Python :: 3.7
Classifier: Programming Language :: Python :: 3.8
Classifier: Programming Language :: Python :: 3.9
Classifier: Programming Language :: Python :: 3.10
Classifier: Programming Language :: Python :: 3.11
Classifier: Programming Language :: Python :: 3.12
License-File: LICENSE
Requires-Dist: bitstring>=3.1
Requires-Dist: pytz
